LICENSE
README.md
setup.py
lib/__init__.py
lib/cli/__init__.py
lib/controllers/__init__.py
lib/controllers/video.py
lib/entities/__init__.py
lib/entities/frame.py
lib/entities/video.py
lib/tests/__init__.py
lib/tests/test_cli.py
lib/tests/test_frame.py
lib/tests/test_video.py
lib/tests/test_video_controller.py
play_video.egg-info/PKG-INFO
play_video.egg-info/SOURCES.txt
play_video.egg-info/dependency_links.txt
play_video.egg-info/entry_points.txt
play_video.egg-info/requires.txt
play_video.egg-info/top_level.txt