Metadata-Version: 2.1
Name: play-video
Version: 1.0.6
Summary: Play video on terminal
Home-page: https://github.com/guilhermewebdev/play
Author: Guilherme Isaías
Author-email: guilherme@guilhermeweb.dev
License: GNU General Public License v3.0
Platform: Linux
Platform: MacOS
Platform: Windows
Classifier: Programming Language :: Python :: 3
Classifier: License :: OSI Approved :: GNU General Public License v3 (GPLv3)
Classifier: Operating System :: OS Independent
Classifier: Natural Language :: English
Classifier: Topic :: Multimedia :: Video :: Display
Classifier: Framework :: Pytest
Requires-Python: >=3.7
License-File: LICENSE
